setup.py
sparkprint/__init__.py
sparkprint.egg-info/PKG-INFO
sparkprint.egg-info/SOURCES.txt
sparkprint.egg-info/dependency_links.txt
sparkprint.egg-info/not-zip-safe
sparkprint.egg-info/requires.txt
sparkprint.egg-info/top_level.txt