Metadata-Version: 1.0
Name: sparkprint
Version: 0.13
Summary: A test of making packages on PyPI
Home-page: http://github.com/CoroBot/sparkprint
Author: meta
Author-email: test@example.com
License: MIT
Platform: UNKNOWN
